[
  {
    "title": "14--CONNECTOR,DUMMY,DEL",
    "solicitation": "N0010426QAB09",
    "state": "Unknown",
    "naics": "333998",
    "value": "Unknown",
    "score": 10
  },
  {
    "title": "Aviation-Grade American Flag with Rigging and Hardware",
    "solicitation": "N0018926QL125",
    "state": "Unknown",
    "naics": "314999",
    "value": "Unknown",
    "score": 10
  },
  {
    "title": "DLA Maritime, NSN 2030-01-644-0786, Console Maintainer, Qty 2 each",
    "solicitation": "SPRMM1-26-Q-HD08",
    "state": "Unknown",
    "naics": "33399",
    "value": "Unknown",
    "score": 10
  },
  {
    "title": "City of McMechen, West Virginia, Stormwater Project - Section 219",
    "solicitation": "W911WN26BA007",
    "state": "Unknown",
    "naics": "237110",
    "value": "Unknown",
    "score": 10
  },
  {
    "title": "Solicitation For: Special Purpose Cable Assembly, NSN 5995-01-120-8558",
    "solicitation": "W912CH-25-R-0184",
    "state": "Unknown",
    "naics": "335931",
    "value": "Unknown",
    "score": 10
  },
  {
    "title": "Solicitation / Extension Notice Submission",
    "solicitation": "N00104-26-R-BJ29-0003",
    "state": "Unknown",
    "naics": "335313",
    "value": "Unknown",
    "score": 10
  },
  {
    "title": "TEARDOWN, EVALUATE, REPAIR AND OR MODIFY",
    "solicitation": "N0010426QQB43",
    "state": "Unknown",
    "naics": "335999",
    "value": "Unknown",
    "score": 10
  },
  {
    "title": "American Fair: Freedom 250 In Bangkok",
    "solicitation": "19TH2026Q0024",
    "state": "Unknown",
    "naics": "561990",
    "value": "Unknown",
    "score": 10
  },
  {
    "title": "Laundering Services for Personnel Coveralls and Maintenance Rags",
    "solicitation": "M00264-26-Q-0057",
    "state": "Unknown",
    "naics": "812320",
    "value": "Unknown",
    "score": 10
  },
  {
    "title": "Enhanced Use Lease for Mineral Processing Facilities",
    "solicitation": "W912-QR-DACA27-1-26-204",
    "state": "Unknown",
    "naics": "531120",
    "value": "Unknown",
    "score": 10
  }
]