[
  {
    "title": "<CANCELLED> NONSKID DECK COVERING ON FLIGHT DECK; REPLACE",
    "solicitation": "N6264926R0035",
    "state": "Unknown",
    "naics": "336611",
    "value": "Unknown",
    "score": 10
  },
  {
    "title": "Helium Leak Detector",
    "solicitation": "WS476837",
    "state": "Unknown",
    "naics": "334513",
    "value": "Unknown",
    "score": 10
  },
  {
    "title": "FILTER ELEMENT,AGEN",
    "solicitation": "N0010426QBQ16",
    "state": "Unknown",
    "naics": "339113",
    "value": "Unknown",
    "score": 10
  },
  {
    "title": "New Jersey Intra Coastal Waterway Bank/Shoreline Stabilization Cape May Canal/Point Pleasant Canal ",
    "solicitation": "W912BU26BA010",
    "state": "Unknown",
    "naics": "237990",
    "value": "Unknown",
    "score": 10
  },
  {
    "title": "Highway 86 Checkpoint Shelter Structure Expansion",
    "solicitation": "70B01C25R00000220_2",
    "state": "Unknown",
    "naics": "236220",
    "value": "Unknown",
    "score": 10
  },
  {
    "title": "ENCODER-DECODER,COM",
    "solicitation": "SPRMM126QKD19",
    "state": "Unknown",
    "naics": "334290",
    "value": "Unknown",
    "score": 10
  },
  {
    "title": "16--HEAT EXCHANGER,AIR, IN REPAIR/MODIFICATION OF",
    "solicitation": "N0038326QNA28",
    "state": "Unknown",
    "naics": "336413",
    "value": "Unknown",
    "score": 10
  },
  {
    "title": "FY26 MDC BROOKLYN BUILDING 4 / DAYTON MANOR Landscaping services",
    "solicitation": "15BBR026Q00000009",
    "state": "Unknown",
    "naics": "561730",
    "value": "Unknown",
    "score": 10
  },
  {
    "title": "CHAIN HOIST MOGAS SYSTEM",
    "solicitation": "N6817126QN029",
    "state": "Unknown",
    "naics": "333923",
    "value": "Unknown",
    "score": 10
  },
  {
    "title": "ADAPTER,PHOTOSENSOR",
    "solicitation": "N0010426QBP92",
    "state": "Unknown",
    "naics": "332919",
    "value": "Unknown",
    "score": 10
  }
]