[
  {
    "title": "SLIDE ASSY,CHASSIS",
    "solicitation": "SPRPA126QXA91",
    "state": "Unknown",
    "naics": "334417",
    "value": "Unknown",
    "score": 10
  },
  {
    "title": "Demolish Vacant Barracks Buildings 532 and 132H Naval Station Great Lakes",
    "solicitation": "N4008526R0090",
    "state": "Unknown",
    "naics": "238910",
    "value": "Unknown",
    "score": 10
  },
  {
    "title": "Notice of Intent/ Criterion Research, LLC.",
    "solicitation": "89303026NEI000093",
    "state": "Unknown",
    "naics": "518210",
    "value": "Unknown",
    "score": 10
  },
  {
    "title": "16--POWER AMPLIFIER ASS, IN REPAIR/MODIFICATION OF",
    "solicitation": "N0038325RD052",
    "state": "Unknown",
    "naics": "336413",
    "value": "Unknown",
    "score": 10
  },
  {
    "title": "Design-Build (DB) Construction Simple Award Task Order Contract (SATOC) in Bulgaria and Romania",
    "solicitation": "W912GB26RA022",
    "state": "Unknown",
    "naics": "236220",
    "value": "Unknown",
    "score": 10
  },
  {
    "title": "Specialized OSINT Tools IDIQ",
    "solicitation": "RFP-002132",
    "state": "Unknown",
    "naics": "513210",
    "value": "Unknown",
    "score": 10
  },
  {
    "title": "U.S. Senate Hair Care Point-of-Sale System",
    "solicitation": "2026-R-007",
    "state": "Unknown",
    "naics": "513210",
    "value": "Unknown",
    "score": 10
  },
  {
    "title": "Forward Hadronic Calorimeter Absorber Structures",
    "solicitation": "MB457842",
    "state": "Unknown",
    "naics": "332999",
    "value": "Unknown",
    "score": 10
  },
  {
    "title": "Hill AFB - Tribal Meeting & Consultation",
    "solicitation": "A060411",
    "state": "Unknown",
    "naics": "541720",
    "value": "Unknown",
    "score": 10
  },
  {
    "title": "PRINTED CIRCUIT BOA",
    "solicitation": "SPRPA126QUA96",
    "state": "Unknown",
    "naics": "334412",
    "value": "Unknown",
    "score": 10
  }
]